massfunc/__init__.py
massfunc/massfunc.py
massfunc-0.2.2.dist-info/licenses/LICENSE
massfunc-0.2.2.dist-info/METADATA
massfunc-0.2.2.dist-info/WHEEL
massfunc-0.2.2.dist-info/top_level.txt
massfunc-0.2.2.dist-info/RECORD
