Metadata-Version: 2.4
Name: massfunc
Version: 0.2.2
Summary: A Python package for cosmological mass function calculations
Author-email: SOYONAOC <onmyojiflow@gmail.com>
License: MIT
Project-URL: Homepage, https://github.com/SOYONAOC/MassFunction
Project-URL: Bug Reports, https://github.com/SOYONAOC/MassFunction/issues
Project-URL: Source Code, https://github.com/SOYONAOC/MassFunction
Project-URL: Documentation, https://massfunc.readthedocs.io/
Classifier: Development Status :: 4 - Beta
Classifier: Intended Audience :: Science/Research
Classifier: License :: OSI Approved :: MIT License
Classifier: Operating System :: OS Independent
Classifier: Programming Language :: Python :: 3
Classifier: Programming Language :: Python :: 3.8
Classifier: Programming Language :: Python :: 3.9
Classifier: Programming Language :: Python :: 3.10
Classifier: Programming Language :: Python :: 3.11
Classifier: Programming Language :: Python :: 3.12
Classifier: Programming Language :: Python :: 3.13
Classifier: Topic :: Scientific/Engineering :: Astronomy
Classifier: Topic :: Scientific/Engineering :: Physics
Requires-Python: >=3.8
License-File: LICENSE
Requires-Dist: numpy>=1.18.0
Requires-Dist: scipy>=1.5.0
Requires-Dist: astropy>=4.0
Requires-Dist: matplotlib>=3.0.0
Requires-Dist: sympy>=1.6.0
Dynamic: license-file
